rai_whoami/__init__.py
rai_whoami/agents/__init__.py
rai_whoami/agents/ros2/__init__.py
rai_whoami/agents/ros2/embodiment_info_agent.py
rai_whoami/agents/ros2/vector_store_retrieval_agent.py
rai_whoami/build_whoami.py
rai_whoami/initialize_docs_directory.py
rai_whoami/models/__init__.py
rai_whoami/models/models.py
rai_whoami/pipeline/__init__.py
rai_whoami/pipeline/pipeline.py
rai_whoami/pipeline/pipeline_builder.py
rai_whoami/processors/__init__.py
rai_whoami/processors/defaults.py
rai_whoami/processors/postprocessors/__init__.py
rai_whoami/processors/postprocessors/base.py
rai_whoami/processors/postprocessors/compressor.py
rai_whoami/processors/postprocessors/style.py
rai_whoami/processors/preprocessors/__init__.py
rai_whoami/processors/preprocessors/base.py
rai_whoami/processors/preprocessors/docs.py
rai_whoami/processors/preprocessors/image.py
rai_whoami/scripts/ros2_embodiment_service.py
rai_whoami/scripts/ros2_vector_store_retrieval_service.py
rai_whoami/tools/__init__.py
rai_whoami/tools/vector_db.py
rai_whoami/vector_db/__init__.py
rai_whoami/vector_db/builder.py
rai_whoami/vector_db/faiss.py
rai_whoami-0.0.5.dist-info/METADATA
rai_whoami-0.0.5.dist-info/WHEEL
rai_whoami-0.0.5.dist-info/entry_points.txt
rai_whoami-0.0.5.dist-info/RECORD
