Metadata-Version: 2.3
Name: rai_whoami
Version: 0.0.5
Summary: Package to extract embodiment information from robot documentation
Author: Maciej Majek
Author-email: maciej.majek@robotec.ai
Requires-Python: >=3.10,<3.13
Classifier: Development Status :: 4 - Beta
Classifier: License :: OSI Approved :: Apache Software License
Classifier: Programming Language :: Python :: 3
Classifier: Programming Language :: Python :: 3.10
Classifier: Programming Language :: Python :: 3.11
Classifier: Programming Language :: Python :: 3.12
Requires-Dist: Pillow
Requires-Dist: PyPDF2
Requires-Dist: PyYAML
Requires-Dist: faiss-cpu
Requires-Dist: langchain
Requires-Dist: pypdf (>=5.4.0,<6.0.0)
